{
	"snippets.ultisnips.pythonPrompt": false,
	"coc.preferences.extensionUpdateCheck": "daily",
	"suggest.noselect": true,
	"suggest.enablePreselect": false,
	"disabledFeatures": true,
	"suggest.completionItemKindLabels": {
		"class": " ",
		"color": " ",
		"constant": " ",
		"default": " ",
		"enum": " ",
		"enumMember": " ",
		"event": "󱑑 ",
		"field": " ",
		"file": " ",
		"folder": " ",
		"function": "󰊕 ",
		"interface": " ",
		"keyword": " ",
		"method": " ",
		"module": " ",
		"operator": " ",
		"property": " ",
		"reference": " ",
		"snippet": " ",
		"struct": " ",
		"text": " ",
		"typeParameter": " ",
		"unit": " ",
		"value": " ",
		"variable": " "
	},
	"diagnostic.signOffset": 1,
	"diagnostic.errorSign": "󰩃 ",
	"diagnostic.warningSign": "󰄛 ",
	"diagnostic.infoSign": " ",
	"diagnostic.hintSign": "󱅯 ",
	"diagnostic.displayByAle": false,
	"diagnostic.refreshOnInsertMode": false,
	"diagnostic.checkCurrentLine": true,
	"diagnostic.virtualTextPrefix": " ❯❯❯ ",
	"diagnostic.virtualText": false,
	"inlayHint.enable": false,
}
